LICENSE
MANIFEST.in
README.md
setup.cfg
setup.py
franz/__init__.py
franz/base.py
franz/event.py
franz/exceptions.py
franz.egg-info/PKG-INFO
franz.egg-info/SOURCES.txt
franz.egg-info/dependency_links.txt
franz.egg-info/requires.txt
franz.egg-info/top_level.txt
franz.egg-info/zip-safe
franz/kafka/__init__.py
franz/kafka/consumer.py
franz/kafka/producer.py
franz/rabbitmq/__init__.py
franz/rabbitmq/consumer.py
franz/rabbitmq/parameters.py
franz/rabbitmq/producer.py