Metadata-Version: 1.1
Name: franz
Version: 0.0.10
Summary: Event broker built on top of kafka and rabbitmq; used to handle micro services message exchange.
Home-page: https://github.com/eshares/franz
Author: Carta, Inc.
Author-email: engineering@carta.com
License: MIT
Download-URL: https://github.com/eshares/franz/tarball/0.0.10
Keywords: microservices broker event kafka rabbitmq
Platform: UNKNOWN
Classifier: Intended Audience :: Developers
Classifier: Topic :: Software Development :: Libraries
Classifier: License :: OSI Approved :: MIT License
Classifier: Programming Language :: Python :: 3
Classifier: Programming Language :: Python :: 3.3
Classifier: Programming Language :: Python :: 3.4
